babamul/__init__.py
babamul/_version.py
babamul/api.py
babamul/avro_utils.py
babamul/config.py
babamul/consumer.py
babamul/cutout_utils.py
babamul/exceptions.py
babamul/models.py
babamul/raw_models.py
babamul/topics.py
babamul-0.1.0a2.dist-info/METADATA
babamul-0.1.0a2.dist-info/WHEEL
babamul-0.1.0a2.dist-info/licenses/LICENSE
babamul-0.1.0a2.dist-info/RECORD
