Metadata-Version: 2.4
Name: babamul
Version: 0.1.0a2
Summary: Python client for consuming ZTF/LSST alerts from BABAMUL Kafka streams
Project-URL: Homepage, https://github.com/boom-astro/babamul
Project-URL: Documentation, https://boom-astro.github.io/babamul
Project-URL: Repository, https://github.com/boom-astro/babamul
Author: BOOM Team
License-Expression: MIT
License-File: LICENSE
Keywords: alerts,astronomy,babamul,kafka,lsst,transients,ztf
Classifier: Development Status :: 4 - Beta
Classifier: Intended Audience :: Science/Research
Classifier: License :: OSI Approved :: MIT License
Classifier: Operating System :: OS Independent
Classifier: Programming Language :: Python :: 3
Classifier: Programming Language :: Python :: 3.10
Classifier: Programming Language :: Python :: 3.11
Classifier: Programming Language :: Python :: 3.12
Classifier: Topic :: Scientific/Engineering :: Astronomy
Requires-Python: >=3.11
Requires-Dist: astropy>=7.2.0
Requires-Dist: confluent-kafka>=2.3.0
Requires-Dist: cramjam>=2.8.0
Requires-Dist: fastavro>=1.9.0
Requires-Dist: matplotlib>=3.8.0
Requires-Dist: pydantic>=2.0.0
Requires-Dist: requests>=2.32.5
Requires-Dist: scipy>=1.17.0
